package/__init__.py
package/main_v1.py
Random_Jij_FCC-0.1.dist-info/LICENSE
Random_Jij_FCC-0.1.dist-info/METADATA
Random_Jij_FCC-0.1.dist-info/WHEEL
Random_Jij_FCC-0.1.dist-info/top_level.txt
Random_Jij_FCC-0.1.dist-info/RECORD
