Metadata-Version: 2.1
Name: Random-Jij-FCC
Version: 0.1
Summary: Generates random Jij for FCC systems
Home-page: https://github.com/pypa/sampleproject
Author: Ankit Izardar
Author-email: ankitizardar@gmail.com
License: UNKNOWN
Project-URL: Bug Tracker, https://github.com/pypa/sampleproject/issues
Platform: UNKNOWN
Classifier: Programming Language :: Python :: 3
Classifier: License :: OSI Approved :: MIT License
Classifier: Operating System :: OS Independent
Requires-Python: >=3.6
License-File: LICENSE
